{
  "id": "af1ed4e9-445c-4924-bcb3-db96ab4b3a56",
  "prevId": "5cb6e6c3-de57-4326-9486-f8ae58035a94",
  "version": "7",
  "dialect": "postgresql",
  "tables": {
    "public.events": {
      "name": "events",
      "schema": "",
      "columns": {
        "id": {
          "name": "id",
          "type": "serial",
          "primaryKey": true,
          "notNull": true
        },
        "title": {
          "name": "title",
          "type": "text",
          "primaryKey": false,
          "notNull": true
        },
        "date": {
          "name": "date",
          "type": "text",
          "primaryKey": false,
          "notNull": true
        },
        "description": {
          "name": "description",
          "type": "text",
          "primaryKey": false,
          "notNull": false
        },
        "created_at": {
          "name": "created_at",
          "type": "timestamp",
          "primaryKey": false,
          "notNull": false,
          "default": "now()"
        }
      },
      "indexes": {},
      "foreignKeys": {},
      "compositePrimaryKeys": {},
      "uniqueConstraints": {},
      "policies": {},
      "checkConstraints": {},
      "isRLSEnabled": false
    },
    "public.feedback_comments": {
      "name": "feedback_comments",
      "schema": "",
      "columns": {
        "id": {
          "name": "id",
          "type": "serial",
          "primaryKey": true,
          "notNull": true
        },
        "feedback_id": {
          "name": "feedback_id",
          "type": "integer",
          "primaryKey": false,
          "notNull": true
        },
        "user_id": {
          "name": "user_id",
          "type": "text",
          "primaryKey": false,
          "notNull": true
        },
        "user_name": {
          "name": "user_name",
          "type": "text",
          "primaryKey": false,
          "notNull": false
        },
        "content": {
          "name": "content",
          "type": "text",
          "primaryKey": false,
          "notNull": true
        },
        "created_at": {
          "name": "created_at",
          "type": "timestamp",
          "primaryKey": false,
          "notNull": false,
          "default": "now()"
        }
      },
      "indexes": {},
      "foreignKeys": {
        "feedback_comments_feedback_id_tutorial_feedback_id_fk": {
          "name": "feedback_comments_feedback_id_tutorial_feedback_id_fk",
          "tableFrom": "feedback_comments",
          "tableTo": "tutorial_feedback",
          "columnsFrom": [
            "feedback_id"
          ],
          "columnsTo": [
            "id"
          ],
          "onDelete": "cascade",
          "onUpdate": "no action"
        }
      },
      "compositePrimaryKeys": {},
      "uniqueConstraints": {},
      "policies": {},
      "checkConstraints": {},
      "isRLSEnabled": false
    },
    "public.global_settings": {
      "name": "global_settings",
      "schema": "",
      "columns": {
        "id": {
          "name": "id",
          "type": "serial",
          "primaryKey": true,
          "notNull": true
        },
        "fetch_range_days": {
          "name": "fetch_range_days",
          "type": "integer",
          "primaryKey": false,
          "notNull": false,
          "default": 30
        },
        "auto_delete_days": {
          "name": "auto_delete_days",
          "type": "integer",
          "primaryKey": false,
          "notNull": false,
          "default": 30
        },
        "smtp_host": {
          "name": "smtp_host",
          "type": "text",
          "primaryKey": false,
          "notNull": false
        },
        "smtp_port": {
          "name": "smtp_port",
          "type": "integer",
          "primaryKey": false,
          "notNull": false
        },
        "smtp_user": {
          "name": "smtp_user",
          "type": "text",
          "primaryKey": false,
          "notNull": false
        },
        "smtp_pass": {
          "name": "smtp_pass",
          "type": "text",
          "primaryKey": false,
          "notNull": false
        },
        "imap_host": {
          "name": "imap_host",
          "type": "text",
          "primaryKey": false,
          "notNull": false
        },
        "imap_port": {
          "name": "imap_port",
          "type": "integer",
          "primaryKey": false,
          "notNull": false
        },
        "imap_secure": {
          "name": "imap_secure",
          "type": "boolean",
          "primaryKey": false,
          "notNull": false,
          "default": true
        },
        "semester_start_date": {
          "name": "semester_start_date",
          "type": "text",
          "primaryKey": false,
          "notNull": false
        },
        "semester_end_date": {
          "name": "semester_end_date",
          "type": "text",
          "primaryKey": false,
          "notNull": false
        },
        "api_token": {
          "name": "api_token",
          "type": "text",
          "primaryKey": false,
          "notNull": false
        }
      },
      "indexes": {},
      "foreignKeys": {},
      "compositePrimaryKeys": {},
      "uniqueConstraints": {},
      "policies": {},
      "checkConstraints": {},
      "isRLSEnabled": false
    },
    "public.major_courses": {
      "name": "major_courses",
      "schema": "",
      "columns": {
        "id": {
          "name": "id",
          "type": "serial",
          "primaryKey": true,
          "notNull": true
        },
        "major_id": {
          "name": "major_id",
          "type": "integer",
          "primaryKey": false,
          "notNull": true
        },
        "subject_id": {
          "name": "subject_id",
          "type": "integer",
          "primaryKey": false,
          "notNull": true
        },
        "optional_group": {
          "name": "optional_group",
          "type": "text",
          "primaryKey": false,
          "notNull": false
        },
        "optional_group_req_count": {
          "name": "optional_group_req_count",
          "type": "integer",
          "primaryKey": false,
          "notNull": false
        }
      },
      "indexes": {},
      "foreignKeys": {
        "major_courses_major_id_majors_id_fk": {
          "name": "major_courses_major_id_majors_id_fk",
          "tableFrom": "major_courses",
          "tableTo": "majors",
          "columnsFrom": [
            "major_id"
          ],
          "columnsTo": [
            "id"
          ],
          "onDelete": "cascade",
          "onUpdate": "no action"
        },
        "major_courses_subject_id_subjects_id_fk": {
          "name": "major_courses_subject_id_subjects_id_fk",
          "tableFrom": "major_courses",
          "tableTo": "subjects",
          "columnsFrom": [
            "subject_id"
          ],
          "columnsTo": [
            "id"
          ],
          "onDelete": "cascade",
          "onUpdate": "no action"
        }
      },
      "compositePrimaryKeys": {},
      "uniqueConstraints": {},
      "policies": {},
      "checkConstraints": {},
      "isRLSEnabled": false
    },
    "public.majors": {
      "name": "majors",
      "schema": "",
      "columns": {
        "id": {
          "name": "id",
          "type": "serial",
          "primaryKey": true,
          "notNull": true
        },
        "name": {
          "name": "name",
          "type": "text",
          "primaryKey": false,
          "notNull": true
        },
        "pdf_url": {
          "name": "pdf_url",
          "type": "text",
          "primaryKey": false,
          "notNull": false
        },
        "created_at": {
          "name": "created_at",
          "type": "timestamp",
          "primaryKey": false,
          "notNull": false,
          "default": "now()"
        }
      },
      "indexes": {},
      "foreignKeys": {},
      "compositePrimaryKeys": {},
      "uniqueConstraints": {},
      "policies": {},
      "checkConstraints": {},
      "isRLSEnabled": false
    },
    "public.news": {
      "name": "news",
      "schema": "",
      "columns": {
        "id": {
          "name": "id",
          "type": "serial",
          "primaryKey": true,
          "notNull": true
        },
        "content": {
          "name": "content",
          "type": "text",
          "primaryKey": false,
          "notNull": true
        },
        "source": {
          "name": "source",
          "type": "text",
          "primaryKey": false,
          "notNull": false
        },
        "author_name": {
          "name": "author_name",
          "type": "text",
          "primaryKey": false,
          "notNull": false
        },
        "author_handle": {
          "name": "author_handle",
          "type": "text",
          "primaryKey": false,
          "notNull": false
        },
        "author_avatar": {
          "name": "author_avatar",
          "type": "text",
          "primaryKey": false,
          "notNull": false
        },
        "image_url": {
          "name": "image_url",
          "type": "text",
          "primaryKey": false,
          "notNull": false
        },
        "video_url": {
          "name": "video_url",
          "type": "text",
          "primaryKey": false,
          "notNull": false
        },
        "date": {
          "name": "date",
          "type": "text",
          "primaryKey": false,
          "notNull": true
        },
        "tweet_id": {
          "name": "tweet_id",
          "type": "text",
          "primaryKey": false,
          "notNull": false
        },
        "created_at": {
          "name": "created_at",
          "type": "timestamp",
          "primaryKey": false,
          "notNull": false,
          "default": "now()"
        }
      },
      "indexes": {},
      "foreignKeys": {},
      "compositePrimaryKeys": {},
      "uniqueConstraints": {
        "news_tweet_id_unique": {
          "name": "news_tweet_id_unique",
          "nullsNotDistinct": false,
          "columns": [
            "tweet_id"
          ]
        }
      },
      "policies": {},
      "checkConstraints": {},
      "isRLSEnabled": false
    },
    "public.news_comments": {
      "name": "news_comments",
      "schema": "",
      "columns": {
        "id": {
          "name": "id",
          "type": "serial",
          "primaryKey": true,
          "notNull": true
        },
        "user_id": {
          "name": "user_id",
          "type": "text",
          "primaryKey": false,
          "notNull": true
        },
        "news_id": {
          "name": "news_id",
          "type": "integer",
          "primaryKey": false,
          "notNull": true
        },
        "content": {
          "name": "content",
          "type": "text",
          "primaryKey": false,
          "notNull": true
        },
        "created_at": {
          "name": "created_at",
          "type": "timestamp",
          "primaryKey": false,
          "notNull": false,
          "default": "now()"
        }
      },
      "indexes": {},
      "foreignKeys": {
        "news_comments_news_id_news_id_fk": {
          "name": "news_comments_news_id_news_id_fk",
          "tableFrom": "news_comments",
          "tableTo": "news",
          "columnsFrom": [
            "news_id"
          ],
          "columnsTo": [
            "id"
          ],
          "onDelete": "cascade",
          "onUpdate": "no action"
        }
      },
      "compositePrimaryKeys": {},
      "uniqueConstraints": {},
      "policies": {},
      "checkConstraints": {},
      "isRLSEnabled": false
    },
    "public.news_likes": {
      "name": "news_likes",
      "schema": "",
      "columns": {
        "id": {
          "name": "id",
          "type": "serial",
          "primaryKey": true,
          "notNull": true
        },
        "user_id": {
          "name": "user_id",
          "type": "text",
          "primaryKey": false,
          "notNull": true
        },
        "news_id": {
          "name": "news_id",
          "type": "integer",
          "primaryKey": false,
          "notNull": true
        },
        "created_at": {
          "name": "created_at",
          "type": "timestamp",
          "primaryKey": false,
          "notNull": false,
          "default": "now()"
        }
      },
      "indexes": {},
      "foreignKeys": {
        "news_likes_news_id_news_id_fk": {
          "name": "news_likes_news_id_news_id_fk",
          "tableFrom": "news_likes",
          "tableTo": "news",
          "columnsFrom": [
            "news_id"
          ],
          "columnsTo": [
            "id"
          ],
          "onDelete": "cascade",
          "onUpdate": "no action"
        }
      },
      "compositePrimaryKeys": {},
      "uniqueConstraints": {
        "news_likes_user_id_news_id_unique": {
          "name": "news_likes_user_id_news_id_unique",
          "nullsNotDistinct": false,
          "columns": [
            "user_id",
            "news_id"
          ]
        }
      },
      "policies": {},
      "checkConstraints": {},
      "isRLSEnabled": false
    },
    "public.news_sources": {
      "name": "news_sources",
      "schema": "",
      "columns": {
        "id": {
          "name": "id",
          "type": "serial",
          "primaryKey": true,
          "notNull": true
        },
        "handle": {
          "name": "handle",
          "type": "text",
          "primaryKey": false,
          "notNull": true
        },
        "is_active": {
          "name": "is_active",
          "type": "boolean",
          "primaryKey": false,
          "notNull": false,
          "default": true
        },
        "profile_pic_url": {
          "name": "profile_pic_url",
          "type": "text",
          "primaryKey": false,
          "notNull": false
        },
        "last_fetched": {
          "name": "last_fetched",
          "type": "timestamp",
          "primaryKey": false,
          "notNull": false
        },
        "created_at": {
          "name": "created_at",
          "type": "timestamp",
          "primaryKey": false,
          "notNull": false,
          "default": "now()"
        }
      },
      "indexes": {},
      "foreignKeys": {},
      "compositePrimaryKeys": {},
      "uniqueConstraints": {
        "news_sources_handle_unique": {
          "name": "news_sources_handle_unique",
          "nullsNotDistinct": false,
          "columns": [
            "handle"
          ]
        }
      },
      "policies": {},
      "checkConstraints": {},
      "isRLSEnabled": false
    },
    "public.subjects": {
      "name": "subjects",
      "schema": "",
      "columns": {
        "id": {
          "name": "id",
          "type": "serial",
          "primaryKey": true,
          "notNull": true
        },
        "code": {
          "name": "code",
          "type": "text",
          "primaryKey": false,
          "notNull": true
        },
        "name": {
          "name": "name",
          "type": "text",
          "primaryKey": false,
          "notNull": true
        },
        "drive_link": {
          "name": "drive_link",
          "type": "text",
          "primaryKey": false,
          "notNull": false
        },
        "whatsapp_link": {
          "name": "whatsapp_link",
          "type": "text",
          "primaryKey": false,
          "notNull": false
        },
        "credit_hours": {
          "name": "credit_hours",
          "type": "integer",
          "primaryKey": false,
          "notNull": false,
          "default": 3
        },
        "level": {
          "name": "level",
          "type": "integer",
          "primaryKey": false,
          "notNull": false
        },
        "created_at": {
          "name": "created_at",
          "type": "timestamp",
          "primaryKey": false,
          "notNull": false,
          "default": "now()"
        }
      },
      "indexes": {},
      "foreignKeys": {},
      "compositePrimaryKeys": {},
      "uniqueConstraints": {},
      "policies": {},
      "checkConstraints": {},
      "isRLSEnabled": false
    },
    "public.tutorial_feedback": {
      "name": "tutorial_feedback",
      "schema": "",
      "columns": {
        "id": {
          "name": "id",
          "type": "serial",
          "primaryKey": true,
          "notNull": true
        },
        "tutorial_id": {
          "name": "tutorial_id",
          "type": "integer",
          "primaryKey": false,
          "notNull": true
        },
        "user_id": {
          "name": "user_id",
          "type": "text",
          "primaryKey": false,
          "notNull": true
        },
        "is_helpful": {
          "name": "is_helpful",
          "type": "boolean",
          "primaryKey": false,
          "notNull": true
        },
        "comment": {
          "name": "comment",
          "type": "text",
          "primaryKey": false,
          "notNull": false
        },
        "created_at": {
          "name": "created_at",
          "type": "timestamp",
          "primaryKey": false,
          "notNull": false,
          "default": "now()"
        }
      },
      "indexes": {},
      "foreignKeys": {
        "tutorial_feedback_tutorial_id_tutorials_id_fk": {
          "name": "tutorial_feedback_tutorial_id_tutorials_id_fk",
          "tableFrom": "tutorial_feedback",
          "tableTo": "tutorials",
          "columnsFrom": [
            "tutorial_id"
          ],
          "columnsTo": [
            "id"
          ],
          "onDelete": "cascade",
          "onUpdate": "no action"
        }
      },
      "compositePrimaryKeys": {},
      "uniqueConstraints": {},
      "policies": {},
      "checkConstraints": {},
      "isRLSEnabled": false
    },
    "public.tutorial_sections": {
      "name": "tutorial_sections",
      "schema": "",
      "columns": {
        "id": {
          "name": "id",
          "type": "serial",
          "primaryKey": true,
          "notNull": true
        },
        "title": {
          "name": "title",
          "type": "text",
          "primaryKey": false,
          "notNull": true
        },
        "icon": {
          "name": "icon",
          "type": "text",
          "primaryKey": false,
          "notNull": true,
          "default": "'GraduationCap'"
        },
        "color": {
          "name": "color",
          "type": "text",
          "primaryKey": false,
          "notNull": true,
          "default": "'text-blue-600 bg-blue-50 border-blue-100/50'"
        },
        "created_at": {
          "name": "created_at",
          "type": "timestamp",
          "primaryKey": false,
          "notNull": false,
          "default": "now()"
        }
      },
      "indexes": {},
      "foreignKeys": {},
      "compositePrimaryKeys": {},
      "uniqueConstraints": {},
      "policies": {},
      "checkConstraints": {},
      "isRLSEnabled": false
    },
    "public.tutorials": {
      "name": "tutorials",
      "schema": "",
      "columns": {
        "id": {
          "name": "id",
          "type": "serial",
          "primaryKey": true,
          "notNull": true
        },
        "section_id": {
          "name": "section_id",
          "type": "integer",
          "primaryKey": false,
          "notNull": true
        },
        "title": {
          "name": "title",
          "type": "text",
          "primaryKey": false,
          "notNull": true
        },
        "description": {
          "name": "description",
          "type": "text",
          "primaryKey": false,
          "notNull": true
        },
        "text": {
          "name": "text",
          "type": "text",
          "primaryKey": false,
          "notNull": true
        },
        "steps": {
          "name": "steps",
          "type": "text",
          "primaryKey": false,
          "notNull": true
        },
        "video_url": {
          "name": "video_url",
          "type": "text",
          "primaryKey": false,
          "notNull": false
        },
        "image_url": {
          "name": "image_url",
          "type": "text",
          "primaryKey": false,
          "notNull": false
        },
        "created_at": {
          "name": "created_at",
          "type": "timestamp",
          "primaryKey": false,
          "notNull": false,
          "default": "now()"
        }
      },
      "indexes": {},
      "foreignKeys": {
        "tutorials_section_id_tutorial_sections_id_fk": {
          "name": "tutorials_section_id_tutorial_sections_id_fk",
          "tableFrom": "tutorials",
          "tableTo": "tutorial_sections",
          "columnsFrom": [
            "section_id"
          ],
          "columnsTo": [
            "id"
          ],
          "onDelete": "cascade",
          "onUpdate": "no action"
        }
      },
      "compositePrimaryKeys": {},
      "uniqueConstraints": {},
      "policies": {},
      "checkConstraints": {},
      "isRLSEnabled": false
    },
    "public.users": {
      "name": "users",
      "schema": "",
      "columns": {
        "id": {
          "name": "id",
          "type": "serial",
          "primaryKey": true,
          "notNull": true
        },
        "uid": {
          "name": "uid",
          "type": "text",
          "primaryKey": false,
          "notNull": true
        },
        "user_name": {
          "name": "user_name",
          "type": "text",
          "primaryKey": false,
          "notNull": false
        },
        "email": {
          "name": "email",
          "type": "text",
          "primaryKey": false,
          "notNull": true
        },
        "password_hash": {
          "name": "password_hash",
          "type": "text",
          "primaryKey": false,
          "notNull": false
        },
        "phone": {
          "name": "phone",
          "type": "text",
          "primaryKey": false,
          "notNull": false
        },
        "major": {
          "name": "major",
          "type": "text",
          "primaryKey": false,
          "notNull": false
        },
        "current_gpa": {
          "name": "current_gpa",
          "type": "varchar(10)",
          "primaryKey": false,
          "notNull": false
        },
        "finished_hours": {
          "name": "finished_hours",
          "type": "integer",
          "primaryKey": false,
          "notNull": false
        },
        "completed_courses": {
          "name": "completed_courses",
          "type": "text",
          "primaryKey": false,
          "notNull": false
        },
        "is_admin": {
          "name": "is_admin",
          "type": "boolean",
          "primaryKey": false,
          "notNull": false,
          "default": false
        },
        "profile_pic_url": {
          "name": "profile_pic_url",
          "type": "text",
          "primaryKey": false,
          "notNull": false
        },
        "created_at": {
          "name": "created_at",
          "type": "timestamp",
          "primaryKey": false,
          "notNull": false,
          "default": "now()"
        }
      },
      "indexes": {},
      "foreignKeys": {},
      "compositePrimaryKeys": {},
      "uniqueConstraints": {
        "users_uid_unique": {
          "name": "users_uid_unique",
          "nullsNotDistinct": false,
          "columns": [
            "uid"
          ]
        },
        "users_email_unique": {
          "name": "users_email_unique",
          "nullsNotDistinct": false,
          "columns": [
            "email"
          ]
        }
      },
      "policies": {},
      "checkConstraints": {},
      "isRLSEnabled": false
    },
    "public.verification_codes": {
      "name": "verification_codes",
      "schema": "",
      "columns": {
        "id": {
          "name": "id",
          "type": "serial",
          "primaryKey": true,
          "notNull": true
        },
        "email": {
          "name": "email",
          "type": "text",
          "primaryKey": false,
          "notNull": true
        },
        "code": {
          "name": "code",
          "type": "text",
          "primaryKey": false,
          "notNull": true
        },
        "expires_at": {
          "name": "expires_at",
          "type": "timestamp",
          "primaryKey": false,
          "notNull": true
        },
        "created_at": {
          "name": "created_at",
          "type": "timestamp",
          "primaryKey": false,
          "notNull": false,
          "default": "now()"
        }
      },
      "indexes": {},
      "foreignKeys": {},
      "compositePrimaryKeys": {},
      "uniqueConstraints": {},
      "policies": {},
      "checkConstraints": {},
      "isRLSEnabled": false
    }
  },
  "enums": {},
  "schemas": {},
  "sequences": {},
  "roles": {},
  "policies": {},
  "views": {},
  "_meta": {
    "columns": {},
    "schemas": {},
    "tables": {}
  }
}